[
  {
    "date": "2025-08-04",
    "video1Id": "dQw4w9WgXcQ",
    "video2Id": "h5LfvCKfbLs",
    "video3Id": "gTGDQrVmPVs",
    "video4Id": "Wp3t9Nwjr_8",
    "video5Id": "rtSrWn7eYbU"
  },
  {
    "date": "2025-08-05",
    "video1Id": "9bZkp7q19f0",
    "video2Id": "kJQP7kiw5Fk",
    "video3Id": "rt-2cxAiPJk",
    "video4Id": "TcMBFSGVi1c",
    "video5Id": "kfVsfOSbJY0"
  },
  {
    "date": "2025-08-06",
    "video1Id": "L_jWHffIx5E",
    "video2Id": "YQHsXMglC9A",
    "video3Id": "hTWKbfoikeg",
    "video4Id": "nfs8NYg7yQM",
    "video5Id": "iik25wqIuFo"
  },
  {
    "date": "2025-08-07",
    "video1Id": "astISOttCQ0",
    "video2Id": "ZZ5LpwO-An4",
    "video3Id": "hFcLyDb6niA",
    "video4Id": "RgKAFK5djSk",
    "video5Id": "BROWqjuTM0g"
  },
  {
    "date": "2025-08-08",
    "video1Id": "y6120QOlsfU",
    "video2Id": "kXYiU_JCYtU",
    "video3Id": "NUYvbT6vTPs",
    "video4Id": "RyFteZf7AcA",
    "video5Id": "CevxZvSJLk8"
  }

]
